[
  {
    "id": "fraseal",
    "level": "/home/riko/S1PlainTextArchive2021/外野新闻/2020/1940765-01[洁厕剂装进饮料瓶，16岁学生一饮而尽].md6",
    "goose": {
      "静夜观星": "1",
      "rainwang": "1"
    }
  },
  {
    "id": "MortarHeadd",
    "level": "/home/riko/S1PlainTextArchive2021/外野新闻/2020/1940765-01[洁厕剂装进饮料瓶，16岁学生一饮而尽].md27",
    "goose": {
      "文本框": "1"
    }
  },
  {
    "id": "盾墙",
    "level": "/home/riko/S1PlainTextArchive2021/外野新闻/2020/1940765-01[洁厕剂装进饮料瓶，16岁学生一饮而尽].md30",
    "goose": {
      "ozo": "-1",
      "坛子漆黑": "1",
      "远处的少年": "-1"
    }
  },
  {
    "id": "東京地方検察庁",
    "level": "/home/riko/S1PlainTextArchive2021/外野新闻/2020/1940765-01[洁厕剂装进饮料瓶，16岁学生一饮而尽].md31",
    "goose": {
      "mustforver": "1"
    }
  },
  {
    "id": "nukacolamania",
    "level": "/home/riko/S1PlainTextArchive2021/外野新闻/2020/1940765-01[洁厕剂装进饮料瓶，16岁学生一饮而尽].md41",
    "goose": {
      "双层天椒皇堡": "1",
      "kenfy612": "1",
      "哈迪斯兜帽": "-1",
      "莉莉橙": "-1"
    }
  },
  {
    "id": "takami",
    "level": "/home/riko/S1PlainTextArchive2021/外野新闻/2020/1940765-01[洁厕剂装进饮料瓶，16岁学生一饮而尽].md50",
    "goose": {
      "pliee": "1"
    }
  },
  {
    "id": "konev",
    "level": "/home/riko/S1PlainTextArchive2021/外野新闻/2020/1940765-01[洁厕剂装进饮料瓶，16岁学生一饮而尽].md94",
    "goose": {
      "泰非力的答复": "1",
      "远处的少年": "-1"
    }
  },
  {
    "id": "折中旗帜鲜明",
    "level": "/home/riko/S1PlainTextArchive2021/外野新闻/2020/1940765-01[洁厕剂装进饮料瓶，16岁学生一饮而尽].md111",
    "goose": {
      "Patlain": "1"
    }
  },
  {
    "id": "MortarHeadd",
    "level": "/home/riko/S1PlainTextArchive2021/外野新闻/2020/1940765-01[洁厕剂装进饮料瓶，16岁学生一饮而尽].md121",
    "goose": {
      "zutama": "-1",
      "Postal": "-1",
      "Yalbsd": "-1",
      "向北子": "1",
      "isaih": "-1",
      "rainwang": "-1"
    }
  }
]