[
  {
    "id": "あのん",
    "level": "/home/riko/S1PlainTextGeneral/虚拟主播专楼/虚拟主播【V综】/1941579[【V10】虚拟YouTuber综合讨论楼にじさんじ周年fes将于2月举办]/1941579-29[【V10】虚拟YouTuber综合讨论楼ホロライブ大规模隐藏录像].md42002",
    "goose": {
      "泡芙好吃": "1"
    }
  },
  {
    "id": "rzrbtk",
    "level": "/home/riko/S1PlainTextGeneral/虚拟主播专楼/虚拟主播【V综】/1941579[【V10】虚拟YouTuber综合讨论楼にじさんじ周年fes将于2月举办]/1941579-29[【V10】虚拟YouTuber综合讨论楼ホロライブ大规模隐藏录像].md42024",
    "goose": {
      "fastary": "1"
    }
  },
  {
    "id": "fromsaitama",
    "level": "/home/riko/S1PlainTextGeneral/虚拟主播专楼/虚拟主播【V综】/1941579[【V10】虚拟YouTuber综合讨论楼にじさんじ周年fes将于2月举办]/1941579-29[【V10】虚拟YouTuber综合讨论楼ホロライブ大规模隐藏录像].md42030",
    "goose": {
      "泡芙好吃": "1"
    }
  },
  {
    "id": "爆炸霊",
    "level": "/home/riko/S1PlainTextGeneral/虚拟主播专楼/虚拟主播【V综】/1941579[【V10】虚拟YouTuber综合讨论楼にじさんじ周年fes将于2月举办]/1941579-29[【V10】虚拟YouTuber综合讨论楼ホロライブ大规模隐藏录像].md42040",
    "goose": {
      "泡芙好吃": "1"
    }
  },
  {
    "id": "erer",
    "level": "/home/riko/S1PlainTextGeneral/虚拟主播专楼/虚拟主播【V综】/1941579[【V10】虚拟YouTuber综合讨论楼にじさんじ周年fes将于2月举办]/1941579-29[【V10】虚拟YouTuber综合讨论楼ホロライブ大规模隐藏录像].md42063",
    "goose": {
      "泡芙好吃": "1"
    }
  },
  {
    "id": "逃离学校",
    "level": "/home/riko/S1PlainTextGeneral/虚拟主播专楼/虚拟主播【V综】/1941579[【V10】虚拟YouTuber综合讨论楼にじさんじ周年fes将于2月举办]/1941579-29[【V10】虚拟YouTuber综合讨论楼ホロライブ大规模隐藏录像].md42111",
    "goose": {
      "泡芙好吃": "1"
    }
  },
  {
    "id": "alcoholic1000",
    "level": "/home/riko/S1PlainTextGeneral/虚拟主播专楼/虚拟主播【V综】/1941579[【V10】虚拟YouTuber综合讨论楼にじさんじ周年fes将于2月举办]/1941579-29[【V10】虚拟YouTuber综合讨论楼ホロライブ大规模隐藏录像].md42115",
    "goose": {
      "黑之和": "1",
      "世界的小哥": "1"
    }
  },
  {
    "id": "alcoholic1000",
    "level": "/home/riko/S1PlainTextGeneral/虚拟主播专楼/虚拟主播【V综】/1941579[【V10】虚拟YouTuber综合讨论楼にじさんじ周年fes将于2月举办]/1941579-29[【V10】虚拟YouTuber综合讨论楼ホロライブ大规模隐藏录像].md42153",
    "goose": {
      "fastary": "1"
    }
  },
  {
    "id": "alcoholic1000",
    "level": "/home/riko/S1PlainTextGeneral/虚拟主播专楼/虚拟主播【V综】/1941579[【V10】虚拟YouTuber综合讨论楼にじさんじ周年fes将于2月举办]/1941579-29[【V10】虚拟YouTuber综合讨论楼ホロライブ大规模隐藏录像].md42214",
    "goose": {
      "fastary": "1",
      "世界的小哥": "1"
    }
  },
  {
    "id": "tiro_finale",
    "level": "/home/riko/S1PlainTextGeneral/虚拟主播专楼/虚拟主播【V综】/1941579[【V10】虚拟YouTuber综合讨论楼にじさんじ周年fes将于2月举办]/1941579-29[【V10】虚拟YouTuber综合讨论楼ホロライブ大规模隐藏录像].md42219",
    "goose": {
      "erer": "1"
    }
  },
  {
    "id": "UnhappyTails",
    "level": "/home/riko/S1PlainTextGeneral/虚拟主播专楼/虚拟主播【V综】/1941579[【V10】虚拟YouTuber综合讨论楼にじさんじ周年fes将于2月举办]/1941579-29[【V10】虚拟YouTuber综合讨论楼ホロライブ大规模隐藏录像].md42321",
    "goose": {
      "泡芙好吃": "1"
    }
  },
  {
    "id": "IDIDIDID",
    "level": "/home/riko/S1PlainTextGeneral/虚拟主播专楼/虚拟主播【V综】/1941579[【V10】虚拟YouTuber综合讨论楼にじさんじ周年fes将于2月举办]/1941579-29[【V10】虚拟YouTuber综合讨论楼ホロライブ大规模隐藏录像].md42337",
    "goose": {
      "yuandi0120": "2"
    }
  },
  {
    "id": "poipanchao",
    "level": "/home/riko/S1PlainTextGeneral/虚拟主播专楼/虚拟主播【V综】/1941579[【V10】虚拟YouTuber综合讨论楼にじさんじ周年fes将于2月举办]/1941579-29[【V10】虚拟YouTuber综合讨论楼ホロライブ大规模隐藏录像].md42343",
    "goose": {
      "alcoholic1000": "1"
    }
  },
  {
    "id": "nevp",
    "level": "/home/riko/S1PlainTextGeneral/虚拟主播专楼/虚拟主播【V综】/1941579[【V10】虚拟YouTuber综合讨论楼にじさんじ周年fes将于2月举办]/1941579-29[【V10】虚拟YouTuber综合讨论楼ホロライブ大规模隐藏录像].md42386",
    "goose": {
      "qq845629713": "1"
    }
  },
  {
    "id": "北山玖公",
    "level": "/home/riko/S1PlainTextGeneral/虚拟主播专楼/虚拟主播【V综】/1941579[【V10】虚拟YouTuber综合讨论楼にじさんじ周年fes将于2月举办]/1941579-29[【V10】虚拟YouTuber综合讨论楼ホロライブ大规模隐藏录像].md42496",
    "goose": {
      "NBXX": "1"
    }
  },
  {
    "id": "erer",
    "level": "/home/riko/S1PlainTextGeneral/虚拟主播专楼/虚拟主播【V综】/1941579[【V10】虚拟YouTuber综合讨论楼にじさんじ周年fes将于2月举办]/1941579-29[【V10】虚拟YouTuber综合讨论楼ホロライブ大规模隐藏录像].md42510",
    "goose": {
      "892065152": "1",
      "泡芙好吃": "1",
      "bluebaby": "1"
    }
  },
  {
    "id": "Alpha_R",
    "level": "/home/riko/S1PlainTextGeneral/虚拟主播专楼/虚拟主播【V综】/1941579[【V10】虚拟YouTuber综合讨论楼にじさんじ周年fes将于2月举办]/1941579-29[【V10】虚拟YouTuber综合讨论楼ホロライブ大规模隐藏录像].md42520",
    "goose": {
      "愛繋璃まつり": "1"
    }
  },
  {
    "id": "tiro_finale",
    "level": "/home/riko/S1PlainTextGeneral/虚拟主播专楼/虚拟主播【V综】/1941579[【V10】虚拟YouTuber综合讨论楼にじさんじ周年fes将于2月举办]/1941579-29[【V10】虚拟YouTuber综合讨论楼ホロライブ大规模隐藏录像].md42523",
    "goose": {
      "泡芙好吃": "1"
    }
  },
  {
    "id": "AloissiolA",
    "level": "/home/riko/S1PlainTextGeneral/虚拟主播专楼/虚拟主播【V综】/1941579[【V10】虚拟YouTuber综合讨论楼にじさんじ周年fes将于2月举办]/1941579-29[【V10】虚拟YouTuber综合讨论楼ホロライブ大规模隐藏录像].md42547",
    "goose": {
      "Suny08": "1"
    }
  },
  {
    "id": "Ketestrait",
    "level": "/home/riko/S1PlainTextGeneral/虚拟主播专楼/虚拟主播【V综】/1941579[【V10】虚拟YouTuber综合讨论楼にじさんじ周年fes将于2月举办]/1941579-29[【V10】虚拟YouTuber综合讨论楼ホロライブ大规模隐藏录像].md42617",
    "goose": {
      "UnhappyTails": "1"
    }
  },
  {
    "id": "Alpha_R",
    "level": "/home/riko/S1PlainTextGeneral/虚拟主播专楼/虚拟主播【V综】/1941579[【V10】虚拟YouTuber综合讨论楼にじさんじ周年fes将于2月举办]/1941579-29[【V10】虚拟YouTuber综合讨论楼ホロライブ大规模隐藏录像].md42688",
    "goose": {
      "泡芙好吃": "1"
    }
  },
  {
    "id": "cherryrain",
    "level": "/home/riko/S1PlainTextGeneral/虚拟主播专楼/虚拟主播【V综】/1941579[【V10】虚拟YouTuber综合讨论楼にじさんじ周年fes将于2月举办]/1941579-29[【V10】虚拟YouTuber综合讨论楼ホロライブ大规模隐藏录像].md42711",
    "goose": {
      "Suny08": "1"
    }
  },
  {
    "id": "SuntoryNomu",
    "level": "/home/riko/S1PlainTextGeneral/虚拟主播专楼/虚拟主播【V综】/1941579[【V10】虚拟YouTuber综合讨论楼にじさんじ周年fes将于2月举办]/1941579-29[【V10】虚拟YouTuber综合讨论楼ホロライブ大规模隐藏录像].md42717",
    "goose": {
      "rzrbtk": "1"
    }
  },
  {
    "id": "虚无缥缈的光阴",
    "level": "/home/riko/S1PlainTextGeneral/虚拟主播专楼/虚拟主播【V综】/1941579[【V10】虚拟YouTuber综合讨论楼にじさんじ周年fes将于2月举办]/1941579-29[【V10】虚拟YouTuber综合讨论楼ホロライブ大规模隐藏录像].md42757",
    "goose": {
      "兔姬姬姬姬姬": "1"
    }
  },
  {
    "id": "proxima",
    "level": "/home/riko/S1PlainTextGeneral/虚拟主播专楼/虚拟主播【V综】/1941579[【V10】虚拟YouTuber综合讨论楼にじさんじ周年fes将于2月举办]/1941579-29[【V10】虚拟YouTuber综合讨论楼ホロライブ大规模隐藏录像].md42774",
    "goose": {
      "泡芙好吃": "1"
    }
  },
  {
    "id": "NBXX",
    "level": "/home/riko/S1PlainTextGeneral/虚拟主播专楼/虚拟主播【V综】/1941579[【V10】虚拟YouTuber综合讨论楼にじさんじ周年fes将于2月举办]/1941579-29[【V10】虚拟YouTuber综合讨论楼ホロライブ大规模隐藏录像].md42813",
    "goose": {
      "与天争锋_LZ": "1",
      "泡芙好吃": "1"
    }
  },
  {
    "id": "SuntoryNomu",
    "level": "/home/riko/S1PlainTextGeneral/虚拟主播专楼/虚拟主播【V综】/1941579[【V10】虚拟YouTuber综合讨论楼にじさんじ周年fes将于2月举办]/1941579-29[【V10】虚拟YouTuber综合讨论楼ホロライブ大规模隐藏录像].md42865",
    "goose": {
      "qq845629713": "1",
      "帕克桑": "1"
    }
  },
  {
    "id": "AloissiolA",
    "level": "/home/riko/S1PlainTextGeneral/虚拟主播专楼/虚拟主播【V综】/1941579[【V10】虚拟YouTuber综合讨论楼にじさんじ周年fes将于2月举办]/1941579-29[【V10】虚拟YouTuber综合讨论楼ホロライブ大规模隐藏录像].md42868",
    "goose": {
      "poipanchao": "1"
    }
  },
  {
    "id": "北極海航路",
    "level": "/home/riko/S1PlainTextGeneral/虚拟主播专楼/虚拟主播【V综】/1941579[【V10】虚拟YouTuber综合讨论楼にじさんじ周年fes将于2月举办]/1941579-29[【V10】虚拟YouTuber综合讨论楼ホロライブ大规模隐藏录像].md42894",
    "goose": {
      "alcoholic1000": "1"
    }
  },
  {
    "id": "winda",
    "level": "/home/riko/S1PlainTextGeneral/虚拟主播专楼/虚拟主播【V综】/1941579[【V10】虚拟YouTuber综合讨论楼にじさんじ周年fes将于2月举办]/1941579-29[【V10】虚拟YouTuber综合讨论楼ホロライブ大规模隐藏录像].md42903",
    "goose": {
      "argaregeasr": "2",
      "stedckk": "-2"
    }
  },
  {
    "id": "bluebaby",
    "level": "/home/riko/S1PlainTextGeneral/虚拟主播专楼/虚拟主播【V综】/1941579[【V10】虚拟YouTuber综合讨论楼にじさんじ周年fes将于2月举办]/1941579-29[【V10】虚拟YouTuber综合讨论楼ホロライブ大规模隐藏录像].md42940",
    "goose": {
      "泡芙好吃": "1"
    }
  },
  {
    "id": "万年2位35P",
    "level": "/home/riko/S1PlainTextGeneral/虚拟主播专楼/虚拟主播【V综】/1941579[【V10】虚拟YouTuber综合讨论楼にじさんじ周年fes将于2月举办]/1941579-29[【V10】虚拟YouTuber综合讨论楼ホロライブ大规模隐藏录像].md42947",
    "goose": {
      "fromsaitama": "1"
    }
  },
  {
    "id": "SuntoryNomu",
    "level": "/home/riko/S1PlainTextGeneral/虚拟主播专楼/虚拟主播【V综】/1941579[【V10】虚拟YouTuber综合讨论楼にじさんじ周年fes将于2月举办]/1941579-29[【V10】虚拟YouTuber综合讨论楼ホロライブ大规模隐藏录像].md42974",
    "goose": {
      "Suny08": "1"
    }
  },
  {
    "id": "cherryrain",
    "level": "/home/riko/S1PlainTextGeneral/虚拟主播专楼/虚拟主播【V综】/1941579[【V10】虚拟YouTuber综合讨论楼にじさんじ周年fes将于2月举办]/1941579-29[【V10】虚拟YouTuber综合讨论楼ホロライブ大规模隐藏录像].md42978",
    "goose": {
      "墨玄i": "1"
    }
  },
  {
    "id": "恶魔娘阿洛",
    "level": "/home/riko/S1PlainTextGeneral/虚拟主播专楼/虚拟主播【V综】/1941579[【V10】虚拟YouTuber综合讨论楼にじさんじ周年fes将于2月举办]/1941579-29[【V10】虚拟YouTuber综合讨论楼ホロライブ大规模隐藏录像].md43002",
    "goose": {
      "空集": "1"
    }
  },
  {
    "id": "墨玄i",
    "level": "/home/riko/S1PlainTextGeneral/虚拟主播专楼/虚拟主播【V综】/1941579[【V10】虚拟YouTuber综合讨论楼にじさんじ周年fes将于2月举办]/1941579-29[【V10】虚拟YouTuber综合讨论楼ホロライブ大规模隐藏录像].md43016",
    "goose": {
      "zilch_ren": "1"
    }
  },
  {
    "id": "SuntoryNomu",
    "level": "/home/riko/S1PlainTextGeneral/虚拟主播专楼/虚拟主播【V综】/1941579[【V10】虚拟YouTuber综合讨论楼にじさんじ周年fes将于2月举办]/1941579-29[【V10】虚拟YouTuber综合讨论楼ホロライブ大规模隐藏录像].md43034",
    "goose": {
      "絵生voice": "1",
      "alcoholic1000": "1"
    }
  },
  {
    "id": "tiro_finale",
    "level": "/home/riko/S1PlainTextGeneral/虚拟主播专楼/虚拟主播【V综】/1941579[【V10】虚拟YouTuber综合讨论楼にじさんじ周年fes将于2月举办]/1941579-29[【V10】虚拟YouTuber综合讨论楼ホロライブ大规模隐藏录像].md43088",
    "goose": {
      "泡芙好吃": "1"
    }
  },
  {
    "id": "Mr.shelter",
    "level": "/home/riko/S1PlainTextGeneral/虚拟主播专楼/虚拟主播【V综】/1941579[【V10】虚拟YouTuber综合讨论楼にじさんじ周年fes将于2月举办]/1941579-29[【V10】虚拟YouTuber综合讨论楼ホロライブ大规模隐藏录像].md43117",
    "goose": {
      "admentus": "1"
    }
  },
  {
    "id": "QWANG",
    "level": "/home/riko/S1PlainTextGeneral/虚拟主播专楼/虚拟主播【V综】/1941579[【V10】虚拟YouTuber综合讨论楼にじさんじ周年fes将于2月举办]/1941579-29[【V10】虚拟YouTuber综合讨论楼ホロライブ大规模隐藏录像].md43156",
    "goose": {
      "mmbk": "1",
      "argaregeasr": "1",
      "sisyphus_": "1",
      "admentus": "1",
      "yuezhi": "1"
    }
  },
  {
    "id": "SuntoryNomu",
    "level": "/home/riko/S1PlainTextGeneral/虚拟主播专楼/虚拟主播【V综】/1941579[【V10】虚拟YouTuber综合讨论楼にじさんじ周年fes将于2月举办]/1941579-29[【V10】虚拟YouTuber综合讨论楼ホロライブ大规模隐藏录像].md43324",
    "goose": {
      "JhIenog": "1",
      "nowaki": "1",
      "UnhappyTails": "1",
      "北山玖公": "1",
      "admentus": "1"
    }
  },
  {
    "id": "alcoholic1000",
    "level": "/home/riko/S1PlainTextGeneral/虚拟主播专楼/虚拟主播【V综】/1941579[【V10】虚拟YouTuber综合讨论楼にじさんじ周年fes将于2月举办]/1941579-29[【V10】虚拟YouTuber综合讨论楼ホロライブ大规模隐藏录像].md43345",
    "goose": {
      "黑之和": "1"
    }
  },
  {
    "id": "泡芙好吃",
    "level": "/home/riko/S1PlainTextGeneral/虚拟主播专楼/虚拟主播【V综】/1941579[【V10】虚拟YouTuber综合讨论楼にじさんじ周年fes将于2月举办]/1941579-29[【V10】虚拟YouTuber综合讨论楼ホロライブ大规模隐藏录像].md43357",
    "goose": {
      "屑屑代沟尼亚": "1",
      "892065152": "1"
    }
  }
]