[
  {
    "id": "朋友",
    "level": "/home/riko/S1PlainTextArchive2021/外野讨论（巨魔）/1981149-01[对于996，钱给够就行，这种想法是不是也是又蠢又坏？].md42",
    "goose": {
      "秦一鸣": "1",
      "尚风悦": "2"
    }
  },
  {
    "id": "alitonz",
    "level": "/home/riko/S1PlainTextArchive2021/外野讨论（巨魔）/1981149-01[对于996，钱给够就行，这种想法是不是也是又蠢又坏？].md44",
    "goose": {
      "pyjq": "1",
      "宗汝": "1",
      "为啥": "1"
    }
  },
  {
    "id": "leans",
    "level": "/home/riko/S1PlainTextArchive2021/外野讨论（巨魔）/1981149-01[对于996，钱给够就行，这种想法是不是也是又蠢又坏？].md67",
    "goose": {
      "Faerire": "1"
    }
  }
]