[
  {
    "id": "miao123177",
    "level": "/home/riko/S1PlainTextArchive2021/外野讨论（巨魔）/1993197-01[掌 机 之 王、万 机 之 王、鸡 王 之 王].md7",
    "goose": {
      "chrono_white": "1",
      "耶酥叼根烟": "1"
    }
  },
  {
    "id": "正直的黄瓜",
    "level": "/home/riko/S1PlainTextArchive2021/外野讨论（巨魔）/1993197-01[掌 机 之 王、万 机 之 王、鸡 王 之 王].md67",
    "goose": {
      "蔷薇下": "-1",
      "老沙鳄鱼": "1"
    }
  },
  {
    "id": "ace8848",
    "level": "/home/riko/S1PlainTextArchive2021/外野讨论（巨魔）/1993197-01[掌 机 之 王、万 机 之 王、鸡 王 之 王].md109",
    "goose": {
      "神道设教": "-1"
    }
  }
]