[
  {
    "id": "",
    "level": "/home/riko/S1PlainTextArchive2021/外野讨论（巨魔）/1995544-01[现在国内90后和00后拥有的条件，历史上来看都少有吧].md1",
    "goose": {
      "伪天然巨魔": "-1",
      "万花谷杂役": "-1",
      "八斤肥肉": "-1",
      "傾慕桃子": "-2",
      "mindclicer": "-2",
      "mimiced": "-1",
      "qds": "-1",
      "Gazzz": "-1",
      "samuel.j": "-1",
      "xsl1099": "-1",
      "燕龙": "-1",
      "verzeni": "-2",
      "五块太贵不买了": "-1"
    }
  },
  {
    "id": "喝水都被呛",
    "level": "/home/riko/S1PlainTextArchive2021/外野讨论（巨魔）/1995544-01[现在国内90后和00后拥有的条件，历史上来看都少有吧].md2",
    "goose": {
      "燕龙": "-1",
      "无敌大法师": "-1"
    }
  },
  {
    "id": "孤蜀安安",
    "level": "/home/riko/S1PlainTextArchive2021/外野讨论（巨魔）/1995544-01[现在国内90后和00后拥有的条件，历史上来看都少有吧].md4",
    "goose": {
      "究极学霸": "-1",
      "燕龙": "-1"
    }
  },
  {
    "id": "Corruptwing",
    "level": "/home/riko/S1PlainTextArchive2021/外野讨论（巨魔）/1995544-01[现在国内90后和00后拥有的条件，历史上来看都少有吧].md23",
    "goose": {
      "无敌大法师": "1"
    }
  }
]