[
  {
    "id": "",
    "level": "/home/riko/S1PlainTextArchive2021/外野讨论（巨魔）/1997447-01[其实比起左脚刹车右脚油门，泥潭还有个纱布认知需要改改].md1",
    "goose": {
      "喝水都被呛": "-1",
      "不灭钻石": "-2",
      "金闪闪": "-2",
      "litely": "-1",
      "amgryn": "-1",
      "leavesf1ying": "-1",
      "无敌小露子": "-1",
      "smwysmwy": "-2",
      "xxad": "-2",
      "duperbigd": "-1",
      "aceback": "-2",
      "近月": "-2",
      "保科智子": "-1",
      "Yinacona": "-1",
      "sheshiro": "-1",
      "ikl": "1",
      "霜落": "-2",
      "Yohane": "-1",
      "asuyan": "1",
      "clllllllun": "-1"
    }
  },
  {
    "id": "飞姆托",
    "level": "/home/riko/S1PlainTextArchive2021/外野讨论（巨魔）/1997447-01[其实比起左脚刹车右脚油门，泥潭还有个纱布认知需要改改].md2",
    "goose": {
      "youjh": "2",
      "罗马还能再战": "-1"
    }
  },
  {
    "id": "sujoju",
    "level": "/home/riko/S1PlainTextArchive2021/外野讨论（巨魔）/1997447-01[其实比起左脚刹车右脚油门，泥潭还有个纱布认知需要改改].md19",
    "goose": {
      "fmonion": "1"
    }
  },
  {
    "id": "goranger",
    "level": "/home/riko/S1PlainTextArchive2021/外野讨论（巨魔）/1997447-01[其实比起左脚刹车右脚油门，泥潭还有个纱布认知需要改改].md35",
    "goose": {
      "Thursday": "-1",
      "youjh": "1",
      "罗马还能再战": "-1"
    }
  },
  {
    "id": "不见不散",
    "level": "/home/riko/S1PlainTextArchive2021/外野讨论（巨魔）/1997447-01[其实比起左脚刹车右脚油门，泥潭还有个纱布认知需要改改].md75",
    "goose": {
      "foxlxr": "1",
      "vorastrix": "2",
      "Nanachi": "2",
      "cdy111222": "1",
      "youjh": "-3"
    }
  }
]