[
  {
    "id": "浅木飞鸟",
    "level": "88",
    "goose": {
      "JimmyJoker": "1",
      "Booorunestud": "1"
    }
  },
  {
    "id": "seudhjs",
    "level": "272",
    "goose": {
      "BigLittle1999": "1"
    }
  },
  {
    "id": "superlink",
    "level": "547",
    "goose": {
      "有口皆悲": "1"
    }
  },
  {
    "id": "kamarus",
    "level": "561",
    "goose": {
      "野々原雛桜": "1",
      "Ditfran": "1"
    }
  },
  {
    "id": "xwr",
    "level": "597",
    "goose": {
      "有口皆悲": "1"
    }
  },
  {
    "id": "xwr",
    "level": "599",
    "goose": {
      "有口皆悲": "1"
    }
  },
  {
    "id": "xwr",
    "level": "602",
    "goose": {
      "LT_Harry": "1",
      "有口皆悲": "1"
    }
  },
  {
    "id": "Ditfran",
    "level": "608",
    "goose": {
      "ammk": "1"
    }
  },
  {
    "id": "巨馍蘸酱",
    "level": "687",
    "goose": {
      "LT_Harry": "1"
    }
  },
  {
    "id": "Icytail_",
    "level": "775",
    "goose": {
      "xwr": "1"
    }
  },
  {
    "id": "findpkq",
    "level": "849",
    "goose": {
      "翼宿一": "1"
    }
  },
  {
    "id": "hikari0805",
    "level": "1092",
    "goose": {
      "luguozhe": "1"
    }
  },
  {
    "id": "kyolanaya",
    "level": "1294",
    "goose": {
      "LT_Harry": "1"
    }
  }
]