[
  {
    "id": "",
    "level": "1",
    "goose": {
      "meltykiss": "-1",
      "kazamatsuri": "-1",
      "千本blur": "2",
      "KanoWu": "-2",
      "yuzhaoping": "-1",
      "sprittee": "-1",
      "朝日Asahi": "-1",
      "kirin0079": "-2",
      "Tengu": "-1",
      "wjhzha": "-2",
      "保科智子": "-1",
      "NPCNPC": "-1"
    }
  },
  {
    "id": "ab6546541",
    "level": "10",
    "goose": {
      "黒髪の後輩": "1",
      "湖底的酒桶": "1",
      "lwflwf": "1"
    }
  },
  {
    "id": "愿闻其翔",
    "level": "13",
    "goose": {
      "一千君": "1"
    }
  },
  {
    "id": "德里达幽灵",
    "level": "14",
    "goose": {
      "DeltaStriker": "1",
      "光的彼端": "1",
      "钢铁的巨神": "1",
      "佐塚間桐": "1"
    }
  },
  {
    "id": "kula01",
    "level": "24",
    "goose": {
      "屌拿星人": "1",
      "lovebati": "1",
      "有点神奇": "1",
      "cedric301": "1",
      "草化木": "1",
      "钢铁的巨神": "1",
      "chronosphere": "1",
      "uhybfv": "1",
      "sohryu": "1",
      "翼宿一": "1",
      "CTRYZEN": "1",
      "杉田悠一": "2",
      "湖底的酒桶": "1",
      "Dank_Memes": "1",
      "你听得到": "1",
      "睡耘居主": "1",
      "本田仁美": "1",
      "bsj1234": "1",
      "looFehT0": "1",
      "nemuru_baka": "1"
    }
  },
  {
    "id": "xyzzy",
    "level": "25",
    "goose": {
      "MAO_DREAMER": "1"
    }
  },
  {
    "id": "freedom_k",
    "level": "49",
    "goose": {
      "睡耘居主": "1"
    }
  },
  {
    "id": "酒瓶止迁",
    "level": "90",
    "goose": {
      "屌拿星人": "1"
    }
  },
  {
    "id": "wssirius",
    "level": "121",
    "goose": {
      "圆圆的金鱼": "1"
    }
  },
  {
    "id": "欧金金",
    "level": "131",
    "goose": {
      "fw3ii9": "1",
      "awy47": "1",
      "蔡赴朝": "1"
    }
  },
  {
    "id": "外道丸",
    "level": "152",
    "goose": {
      "bearsnowk": "-2",
      "毛玉H": "-1"
    }
  },
  {
    "id": "外道丸",
    "level": "161",
    "goose": {
      "國立中央大學": "-1"
    }
  }
]