[
  {
    "id": "icchhp1983",
    "level": "/home/riko/S1PlainTextArchive2021/外野讨论（巨魔）/1983499-01[(代孕联想)人类对自己的身体有何种程度的处理权力？].md5",
    "goose": {
      "hellgate22": "-1",
      "饭来张口": "1",
      "poppin": "-1",
      "暗影之诗": "1",
      "fmonion": "1",
      "wolftooth": "-1"
    }
  },
  {
    "id": "f15",
    "level": "/home/riko/S1PlainTextArchive2021/外野讨论（巨魔）/1983499-01[(代孕联想)人类对自己的身体有何种程度的处理权力？].md22",
    "goose": {
      "莉莉橙": "1",
      "秦方": "1"
    }
  },
  {
    "id": "远野四季",
    "level": "/home/riko/S1PlainTextArchive2021/外野讨论（巨魔）/1983499-01[(代孕联想)人类对自己的身体有何种程度的处理权力？].md33",
    "goose": {
      "一片秋天的枫叶": "1",
      "ACFUNBILI": "1",
      "HedyL": "1",
      "xxren1": "1",
      "ビーパパス": "2"
    }
  },
  {
    "id": "巨魔",
    "level": "/home/riko/S1PlainTextArchive2021/外野讨论（巨魔）/1983499-01[(代孕联想)人类对自己的身体有何种程度的处理权力？].md39",
    "goose": {
      "beater": "1"
    }
  },
  {
    "id": "雪霜",
    "level": "/home/riko/S1PlainTextArchive2021/外野讨论（巨魔）/1983499-01[(代孕联想)人类对自己的身体有何种程度的处理权力？].md74",
    "goose": {
      "pzk": "1"
    }
  }
]