[
  {
    "id": "",
    "level": "/home/riko/S1PlainTextArchive2021/外野讨论（巨魔）/2007510-01[被不要脸毛碰瓷了！！等我回过神来它已经在我家阳台了！].md1",
    "goose": {
      "King5268": "1",
      "罗马还能再战": "1",
      "DeepRed": "1",
      "消防": "2",
      "flyzzhj": "1",
      "开起": "1"
    }
  },
  {
    "id": "baozi268369重练",
    "level": "/home/riko/S1PlainTextArchive2021/外野讨论（巨魔）/2007510-01[被不要脸毛碰瓷了！！等我回过神来它已经在我家阳台了！].md22",
    "goose": {
      "wongc_": "1",
      "taco旦那": "1",
      "kvll32": "1",
      "loaflace": "1",
      "deadpig": "1",
      "消防": "2",
      "洛天": "1",
      "钞君": "1",
      "宗汝": "1",
      "慕兰": "1",
      "regular": "1",
      "神勇无敌饶铁牛": "1",
      "shyso": "2",
      "逗比宁": "1",
      "Tree洞": "2",
      "jmian": "1",
      "ltycomputer": "1",
      "ishikawa_k": "1",
      "失踪": "1",
      "cedric301": "1"
    }
  },
  {
    "id": "septer",
    "level": "/home/riko/S1PlainTextArchive2021/外野讨论（巨魔）/2007510-01[被不要脸毛碰瓷了！！等我回过神来它已经在我家阳台了！].md39",
    "goose": {
      "kumwoo": "1"
    }
  },
  {
    "id": "baozi268369重练",
    "level": "/home/riko/S1PlainTextArchive2021/外野讨论（巨魔）/2007510-01[被不要脸毛碰瓷了！！等我回过神来它已经在我家阳台了！].md56",
    "goose": {
      "okandgo": "1",
      "消防": "1"
    }
  },
  {
    "id": "baozi268369重练",
    "level": "/home/riko/S1PlainTextArchive2021/外野讨论（巨魔）/2007510-01[被不要脸毛碰瓷了！！等我回过神来它已经在我家阳台了！].md77",
    "goose": {
      "shyso": "1"
    }
  },
  {
    "id": "baozi268369重练",
    "level": "/home/riko/S1PlainTextArchive2021/外野讨论（巨魔）/2007510-01[被不要脸毛碰瓷了！！等我回过神来它已经在我家阳台了！].md83",
    "goose": {
      "钞君": "1",
      "DEMOxN": "2"
    }
  }
]