[
  {
    "id": "莫洛骑士",
    "level": "/home/riko/S1PlainTextGeneral/虚拟主播专楼/虚拟主播【Asoul】/2010146[【A12】A-SOUL讨论楼（6月18日 20：00 向晚第五人格联动）]/2010146-08[【A12】A-SOUL讨论楼（6月18日 20：00 向晚第五人格联动）].md10529",
    "goose": {
      "凑君胖次真好闻": "1",
      "RoyFT": "1",
      "小憨1": "1"
    }
  },
  {
    "id": "今天吃哪个嘉然",
    "level": "/home/riko/S1PlainTextGeneral/虚拟主播专楼/虚拟主播【Asoul】/2010146[【A12】A-SOUL讨论楼（6月18日 20：00 向晚第五人格联动）]/2010146-08[【A12】A-SOUL讨论楼（6月18日 20：00 向晚第五人格联动）].md10621",
    "goose": {
      "安姆闲人": "1"
    }
  },
  {
    "id": "vegetht",
    "level": "/home/riko/S1PlainTextGeneral/虚拟主播专楼/虚拟主播【Asoul】/2010146[【A12】A-SOUL讨论楼（6月18日 20：00 向晚第五人格联动）]/2010146-08[【A12】A-SOUL讨论楼（6月18日 20：00 向晚第五人格联动）].md10770",
    "goose": {
      "孤睾嘤雄": "-1",
      "nowaki": "-2",
      "凑君胖次真好闻": "1"
    }
  },
  {
    "id": "伊可费斯",
    "level": "/home/riko/S1PlainTextGeneral/虚拟主播专楼/虚拟主播【Asoul】/2010146[【A12】A-SOUL讨论楼（6月18日 20：00 向晚第五人格联动）]/2010146-08[【A12】A-SOUL讨论楼（6月18日 20：00 向晚第五人格联动）].md10802",
    "goose": {
      "今天吃哪个嘉然": "1"
    }
  },
  {
    "id": "Doraknight",
    "level": "/home/riko/S1PlainTextGeneral/虚拟主播专楼/虚拟主播【Asoul】/2010146[【A12】A-SOUL讨论楼（6月18日 20：00 向晚第五人格联动）]/2010146-08[【A12】A-SOUL讨论楼（6月18日 20：00 向晚第五人格联动）].md10815",
    "goose": {
      "孤睾嘤雄": "-1"
    }
  },
  {
    "id": "今天吃哪个嘉然",
    "level": "/home/riko/S1PlainTextGeneral/虚拟主播专楼/虚拟主播【Asoul】/2010146[【A12】A-SOUL讨论楼（6月18日 20：00 向晚第五人格联动）]/2010146-08[【A12】A-SOUL讨论楼（6月18日 20：00 向晚第五人格联动）].md11222",
    "goose": {
      "RoyFT": "1"
    }
  },
  {
    "id": "小憨1",
    "level": "/home/riko/S1PlainTextGeneral/虚拟主播专楼/虚拟主播【Asoul】/2010146[【A12】A-SOUL讨论楼（6月18日 20：00 向晚第五人格联动）]/2010146-08[【A12】A-SOUL讨论楼（6月18日 20：00 向晚第五人格联动）].md11245",
    "goose": {
      "单脚着地": "1",
      "空气先生": "1"
    }
  },
  {
    "id": "莫洛骑士",
    "level": "/home/riko/S1PlainTextGeneral/虚拟主播专楼/虚拟主播【Asoul】/2010146[【A12】A-SOUL讨论楼（6月18日 20：00 向晚第五人格联动）]/2010146-08[【A12】A-SOUL讨论楼（6月18日 20：00 向晚第五人格联动）].md11250",
    "goose": {
      "追风小星星": "1"
    }
  },
  {
    "id": "Labborn",
    "level": "/home/riko/S1PlainTextGeneral/虚拟主播专楼/虚拟主播【Asoul】/2010146[【A12】A-SOUL讨论楼（6月18日 20：00 向晚第五人格联动）]/2010146-08[【A12】A-SOUL讨论楼（6月18日 20：00 向晚第五人格联动）].md11514",
    "goose": {
      "海底铁锚": "1",
      "单脚着地": "1"
    }
  },
  {
    "id": "德里达幽灵",
    "level": "/home/riko/S1PlainTextGeneral/虚拟主播专楼/虚拟主播【Asoul】/2010146[【A12】A-SOUL讨论楼（6月18日 20：00 向晚第五人格联动）]/2010146-08[【A12】A-SOUL讨论楼（6月18日 20：00 向晚第五人格联动）].md11607",
    "goose": {
      "单脚着地": "1",
      "安姆闲人": "1"
    }
  },
  {
    "id": "黄色禁区",
    "level": "/home/riko/S1PlainTextGeneral/虚拟主播专楼/虚拟主播【Asoul】/2010146[【A12】A-SOUL讨论楼（6月18日 20：00 向晚第五人格联动）]/2010146-08[【A12】A-SOUL讨论楼（6月18日 20：00 向晚第五人格联动）].md11758",
    "goose": {
      "制作人": "1"
    }
  },
  {
    "id": "德里达幽灵",
    "level": "/home/riko/S1PlainTextGeneral/虚拟主播专楼/虚拟主播【Asoul】/2010146[【A12】A-SOUL讨论楼（6月18日 20：00 向晚第五人格联动）]/2010146-08[【A12】A-SOUL讨论楼（6月18日 20：00 向晚第五人格联动）].md11801",
    "goose": {
      "今天吃哪个嘉然": "1",
      "安姆闲人": "1"
    }
  },
  {
    "id": "是谁的书画",
    "level": "/home/riko/S1PlainTextGeneral/虚拟主播专楼/虚拟主播【Asoul】/2010146[【A12】A-SOUL讨论楼（6月18日 20：00 向晚第五人格联动）]/2010146-08[【A12】A-SOUL讨论楼（6月18日 20：00 向晚第五人格联动）].md11804",
    "goose": {
      "太对了": "1"
    }
  },
  {
    "id": "天邪鬼",
    "level": "/home/riko/S1PlainTextGeneral/虚拟主播专楼/虚拟主播【Asoul】/2010146[【A12】A-SOUL讨论楼（6月18日 20：00 向晚第五人格联动）]/2010146-08[【A12】A-SOUL讨论楼（6月18日 20：00 向晚第五人格联动）].md11805",
    "goose": {
      "yuzu98k": "1"
    }
  },
  {
    "id": "Kitadoom",
    "level": "/home/riko/S1PlainTextGeneral/虚拟主播专楼/虚拟主播【Asoul】/2010146[【A12】A-SOUL讨论楼（6月18日 20：00 向晚第五人格联动）]/2010146-08[【A12】A-SOUL讨论楼（6月18日 20：00 向晚第五人格联动）].md11832",
    "goose": {
      "physi1202": "1"
    }
  },
  {
    "id": "Hanzong",
    "level": "/home/riko/S1PlainTextGeneral/虚拟主播专楼/虚拟主播【Asoul】/2010146[【A12】A-SOUL讨论楼（6月18日 20：00 向晚第五人格联动）]/2010146-08[【A12】A-SOUL讨论楼（6月18日 20：00 向晚第五人格联动）].md11875",
    "goose": {
      "ti-82": "-82",
      "咲喵": "1",
      "Y_Curiosity": "1",
      "Kitadoom": "1",
      "406129465": "3"
    }
  },
  {
    "id": "Nanachi",
    "level": "/home/riko/S1PlainTextGeneral/虚拟主播专楼/虚拟主播【Asoul】/2010146[【A12】A-SOUL讨论楼（6月18日 20：00 向晚第五人格联动）]/2010146-08[【A12】A-SOUL讨论楼（6月18日 20：00 向晚第五人格联动）].md11966",
    "goose": {
      "Kitadoom": "1"
    }
  }
]