[
  {
    "id": "iamthegodthego",
    "level": "/home/riko/S1PlainTextArchive2021/a无法访问的帖子/2011811-01[你对ACG作品中女性胸部大小的喜好是？].md16",
    "goose": {
      "Unlight": "1"
    }
  },
  {
    "id": "lipo",
    "level": "/home/riko/S1PlainTextArchive2021/a无法访问的帖子/2011811-01[你对ACG作品中女性胸部大小的喜好是？].md35",
    "goose": {
      "exiaexa": "1",
      "cheatdeath3": "1",
      "霍亨索伦亲王": "1",
      "otakuzhou": "2",
      "Melisandre": "1",
      "夜游宫": "1"
    }
  },
  {
    "id": "仟音一心",
    "level": "/home/riko/S1PlainTextArchive2021/a无法访问的帖子/2011811-01[你对ACG作品中女性胸部大小的喜好是？].md54",
    "goose": {
      "maverickhunter": "1"
    }
  },
  {
    "id": "弗兰秀秀",
    "level": "/home/riko/S1PlainTextArchive2021/a无法访问的帖子/2011811-01[你对ACG作品中女性胸部大小的喜好是？].md57",
    "goose": {
      "帕林马哲理": "2"
    }
  }
]